{
   "$typename": "Rules",
   "name": "r2",
   "Rules": [
      {
         "$typename": "CheckingRule",
         "name": "sqs",
         "description": "",
         "check": {
            "$typename": "AttributeRef",
            "attr": "Name"
         }
      },
      {
         "$typename": "CheckingRule",
         "name": "b",
         "description": "",
         "check": {
            "$typename": "AttributeRef",
            "attr": null
         }
      },
      {
         "$typename": "CheckingRule",
         "name": "a",
         "description": "",
         "check": null
      },
      {
         "$typename": "IfThenElseRule",
         "name": "",
         "description": "",
         "IfStatement": {
            "$typename": "IfStatement",
            "name": "",
            "Condition": {
               "$typename": "CheckingRuleCall",
               "rule": null
            },
            "ThenStatements": [],
            "ElseStatements": []
         }
      }
   ],
   "imports": "Entities",
   "forEntity": null
}