{
   "serializationFormatVersion": "2023.1",
   "languages": [
      {
         "key": "-key-protocol",
         "version": "2023.1"
      }
   ],
   "nodes": [
      {
         "id": "ID-7",
         "classifier": {
            "language": "-key-protocol",
            "version": "2023.1",
            "key": "-key-MessageGroup"
         },
         "properties": [
            {
               "property": {
                  "language": "-key-protocol",
                  "version": "2023.1",
                  "key": "-key-MessageGroup-name"
               },
               "value": "Command"
            },
            {
               "property": {
                  "language": "-key-protocol",
                  "version": "2023.1",
                  "key": "-key-MessageGroup-taggedUnionProperty"
               },
               "value": "messageKind"
            }
         ],
         "containments": [
            {
               "containment": {
                  "language": "-key-protocol",
                  "version": "2023.1",
                  "key": "-key-MessageGroup-messages"
               },
               "children": [
                  "ID-17",
                  "ID-24",
                  "ID-93",
                  "ID-91",
                  "ID-114",
                  "ID-92",
                  "ID-109"
               ]
            },
            {
               "containment": {
                  "language": "-key-protocol",
                  "version": "2023.1",
                  "key": "-key-MessageGroup-sharedProperties"
               },
               "children": [
                  "ID-8",
                  "ID-9",
                  "ID-16"
               ]
            }
         ],
         "references": [],
         "annotations": [],
         "parent": null
      },
      {
         "id": "ID-17",
         "classifier": {
            "language": "-key-protocol",
            "version": "2023.1",
            "key": "-key-ObjectType"
         },
         "properties": [
            {
               "property": {
                  "language": "-key-protocol",
                  "version": "2023.1",
                  "key": "-key-Type-name"
               },
               "value": "ChangeClassifier"
            }
         ],
         "containments": [
            {
               "containment": {
                  "language": "-key-protocol",
                  "version": "2023.1",
                  "key": "-key-ObjectType-properties"
               },
               "children": [
                  "ID-18",
                  "ID-23"
               ]
            }
         ],
         "references": [],
         "annotations": [],
         "parent": "ID-7"
      },
      {
         "id": "ID-18",
         "classifier": {
            "language": "-key-protocol",
            "version": "2023.1",
            "key": "-key-PropertyDef"
         },
         "properties": [
            {
               "property": {
                  "language": "-key-protocol",
                  "version": "2023.1",
                  "key": "-key-PropertyDef-name"
               },
               "value": "newClassifier"
            },
            {
               "property": {
                  "language": "-key-protocol",
                  "version": "2023.1",
                  "key": "-key-PropertyDef-mayBeNull"
               },
               "value": "false"
            },
            {
               "property": {
                  "language": "-key-protocol",
                  "version": "2023.1",
                  "key": "-key-PropertyDef-isList"
               },
               "value": "false"
            },
            {
               "property": {
                  "language": "-key-protocol",
                  "version": "2023.1",
                  "key": "-key-PropertyDef-isOptional"
               },
               "value": "false"
            },
            {
               "property": {
                  "language": "-key-protocol",
                  "version": "2023.1",
                  "key": "-key-PropertyDef-validate"
               },
               "value": ""
            }
         ],
         "containments": [],
         "references": [
            {
               "reference": {
                  "language": "-key-protocol",
                  "version": "2023.1",
                  "key": "-key-PropertyDef-type"
               },
               "targets": [
                  {
                     "resolveInfo": "LionWebJsonPointer",
                     "reference": "ID-20"
                  }
               ]
            }
         ],
         "annotations": [],
         "parent": "ID-17"
      },
      {
         "id": "ID-23",
         "classifier": {
            "language": "-key-protocol",
            "version": "2023.1",
            "key": "-key-PropertyDef"
         },
         "properties": [
            {
               "property": {
                  "language": "-key-protocol",
                  "version": "2023.1",
                  "key": "-key-PropertyDef-name"
               },
               "value": "node"
            },
            {
               "property": {
                  "language": "-key-protocol",
                  "version": "2023.1",
                  "key": "-key-PropertyDef-mayBeNull"
               },
               "value": "false"
            },
            {
               "property": {
                  "language": "-key-protocol",
                  "version": "2023.1",
                  "key": "-key-PropertyDef-isList"
               },
               "value": "false"
            },
            {
               "property": {
                  "language": "-key-protocol",
                  "version": "2023.1",
                  "key": "-key-PropertyDef-isOptional"
               },
               "value": "false"
            },
            {
               "property": {
                  "language": "-key-protocol",
                  "version": "2023.1",
                  "key": "-key-PropertyDef-validate"
               },
               "value": ""
            }
         ],
         "containments": [],
         "references": [
            {
               "reference": {
                  "language": "-key-protocol",
                  "version": "2023.1",
                  "key": "-key-PropertyDef-type"
               },
               "targets": [
                  {
                     "resolveInfo": "LionWebId",
                     "reference": "ID-22"
                  }
               ]
            }
         ],
         "annotations": [],
         "parent": "ID-17"
      },
      {
         "id": "ID-24",
         "classifier": {
            "language": "-key-protocol",
            "version": "2023.1",
            "key": "-key-ObjectType"
         },
         "properties": [
            {
               "property": {
                  "language": "-key-protocol",
                  "version": "2023.1",
                  "key": "-key-Type-name"
               },
               "value": "AddProperty"
            }
         ],
         "containments": [
            {
               "containment": {
                  "language": "-key-protocol",
                  "version": "2023.1",
                  "key": "-key-ObjectType-properties"
               },
               "children": [
                  "ID-25",
                  "ID-27",
                  "ID-28"
               ]
            }
         ],
         "references": [],
         "annotations": [],
         "parent": "ID-7"
      },
      {
         "id": "ID-25",
         "classifier": {
            "language": "-key-protocol",
            "version": "2023.1",
            "key": "-key-PropertyDef"
         },
         "properties": [
            {
               "property": {
                  "language": "-key-protocol",
                  "version": "2023.1",
                  "key": "-key-PropertyDef-name"
               },
               "value": "node"
            },
            {
               "property": {
                  "language": "-key-protocol",
                  "version": "2023.1",
                  "key": "-key-PropertyDef-mayBeNull"
               },
               "value": "false"
            },
            {
               "property": {
                  "language": "-key-protocol",
                  "version": "2023.1",
                  "key": "-key-PropertyDef-isList"
               },
               "value": "false"
            },
            {
               "property": {
                  "language": "-key-protocol",
                  "version": "2023.1",
                  "key": "-key-PropertyDef-isOptional"
               },
               "value": "false"
            },
            {
               "property": {
                  "language": "-key-protocol",
                  "version": "2023.1",
                  "key": "-key-PropertyDef-validate"
               },
               "value": ""
            }
         ],
         "containments": [],
         "references": [
            {
               "reference": {
                  "language": "-key-protocol",
                  "version": "2023.1",
                  "key": "-key-PropertyDef-type"
               },
               "targets": [
                  {
                     "resolveInfo": "LionWebId",
                     "reference": "ID-22"
                  }
               ]
            }
         ],
         "annotations": [],
         "parent": "ID-24"
      },
      {
         "id": "ID-27",
         "classifier": {
            "language": "-key-protocol",
            "version": "2023.1",
            "key": "-key-PropertyDef"
         },
         "properties": [
            {
               "property": {
                  "language": "-key-protocol",
                  "version": "2023.1",
                  "key": "-key-PropertyDef-name"
               },
               "value": "property"
            },
            {
               "property": {
                  "language": "-key-protocol",
                  "version": "2023.1",
                  "key": "-key-PropertyDef-mayBeNull"
               },
               "value": "false"
            },
            {
               "property": {
                  "language": "-key-protocol",
                  "version": "2023.1",
                  "key": "-key-PropertyDef-isList"
               },
               "value": "false"
            },
            {
               "property": {
                  "language": "-key-protocol",
                  "version": "2023.1",
                  "key": "-key-PropertyDef-isOptional"
               },
               "value": "false"
            },
            {
               "property": {
                  "language": "-key-protocol",
                  "version": "2023.1",
                  "key": "-key-PropertyDef-validate"
               },
               "value": ""
            }
         ],
         "containments": [],
         "references": [
            {
               "reference": {
                  "language": "-key-protocol",
                  "version": "2023.1",
                  "key": "-key-PropertyDef-type"
               },
               "targets": [
                  {
                     "resolveInfo": "LionWebJsonPointer",
                     "reference": "ID-20"
                  }
               ]
            }
         ],
         "annotations": [],
         "parent": "ID-24"
      },
      {
         "id": "ID-28",
         "classifier": {
            "language": "-key-protocol",
            "version": "2023.1",
            "key": "-key-PropertyDef"
         },
         "properties": [
            {
               "property": {
                  "language": "-key-protocol",
                  "version": "2023.1",
                  "key": "-key-PropertyDef-name"
               },
               "value": "newValue"
            },
            {
               "property": {
                  "language": "-key-protocol",
                  "version": "2023.1",
                  "key": "-key-PropertyDef-mayBeNull"
               },
               "value": "false"
            },
            {
               "property": {
                  "language": "-key-protocol",
                  "version": "2023.1",
                  "key": "-key-PropertyDef-isList"
               },
               "value": "false"
            },
            {
               "property": {
                  "language": "-key-protocol",
                  "version": "2023.1",
                  "key": "-key-PropertyDef-isOptional"
               },
               "value": "false"
            },
            {
               "property": {
                  "language": "-key-protocol",
                  "version": "2023.1",
                  "key": "-key-PropertyDef-validate"
               },
               "value": ""
            }
         ],
         "containments": [],
         "references": [
            {
               "reference": {
                  "language": "-key-protocol",
                  "version": "2023.1",
                  "key": "-key-PropertyDef-type"
               },
               "targets": [
                  {
                     "resolveInfo": "String",
                     "reference": "ID-3"
                  }
               ]
            }
         ],
         "annotations": [],
         "parent": "ID-24"
      },
      {
         "id": "ID-93",
         "classifier": {
            "language": "-key-protocol",
            "version": "2023.1",
            "key": "-key-ObjectType"
         },
         "properties": [
            {
               "property": {
                  "language": "-key-protocol",
                  "version": "2023.1",
                  "key": "-key-Type-name"
               },
               "value": "ChangeProperty"
            }
         ],
         "containments": [
            {
               "containment": {
                  "language": "-key-protocol",
                  "version": "2023.1",
                  "key": "-key-ObjectType-properties"
               },
               "children": [
                  "ID-94",
                  "ID-95",
                  "ID-96"
               ]
            }
         ],
         "references": [],
         "annotations": [],
         "parent": "ID-7"
      },
      {
         "id": "ID-94",
         "classifier": {
            "language": "-key-protocol",
            "version": "2023.1",
            "key": "-key-PropertyDef"
         },
         "properties": [
            {
               "property": {
                  "language": "-key-protocol",
                  "version": "2023.1",
                  "key": "-key-PropertyDef-name"
               },
               "value": "node"
            },
            {
               "property": {
                  "language": "-key-protocol",
                  "version": "2023.1",
                  "key": "-key-PropertyDef-mayBeNull"
               },
               "value": "false"
            },
            {
               "property": {
                  "language": "-key-protocol",
                  "version": "2023.1",
                  "key": "-key-PropertyDef-isList"
               },
               "value": "false"
            },
            {
               "property": {
                  "language": "-key-protocol",
                  "version": "2023.1",
                  "key": "-key-PropertyDef-isOptional"
               },
               "value": "false"
            },
            {
               "property": {
                  "language": "-key-protocol",
                  "version": "2023.1",
                  "key": "-key-PropertyDef-validate"
               },
               "value": ""
            }
         ],
         "containments": [],
         "references": [
            {
               "reference": {
                  "language": "-key-protocol",
                  "version": "2023.1",
                  "key": "-key-PropertyDef-type"
               },
               "targets": [
                  {
                     "resolveInfo": "LionWebId",
                     "reference": "ID-22"
                  }
               ]
            }
         ],
         "annotations": [],
         "parent": "ID-93"
      },
      {
         "id": "ID-95",
         "classifier": {
            "language": "-key-protocol",
            "version": "2023.1",
            "key": "-key-PropertyDef"
         },
         "properties": [
            {
               "property": {
                  "language": "-key-protocol",
                  "version": "2023.1",
                  "key": "-key-PropertyDef-name"
               },
               "value": "property"
            },
            {
               "property": {
                  "language": "-key-protocol",
                  "version": "2023.1",
                  "key": "-key-PropertyDef-mayBeNull"
               },
               "value": "false"
            },
            {
               "property": {
                  "language": "-key-protocol",
                  "version": "2023.1",
                  "key": "-key-PropertyDef-isList"
               },
               "value": "false"
            },
            {
               "property": {
                  "language": "-key-protocol",
                  "version": "2023.1",
                  "key": "-key-PropertyDef-isOptional"
               },
               "value": "false"
            },
            {
               "property": {
                  "language": "-key-protocol",
                  "version": "2023.1",
                  "key": "-key-PropertyDef-validate"
               },
               "value": ""
            }
         ],
         "containments": [],
         "references": [
            {
               "reference": {
                  "language": "-key-protocol",
                  "version": "2023.1",
                  "key": "-key-PropertyDef-type"
               },
               "targets": [
                  {
                     "resolveInfo": "LionWebJsonPointer",
                     "reference": "ID-20"
                  }
               ]
            }
         ],
         "annotations": [],
         "parent": "ID-93"
      },
      {
         "id": "ID-96",
         "classifier": {
            "language": "-key-protocol",
            "version": "2023.1",
            "key": "-key-PropertyDef"
         },
         "properties": [
            {
               "property": {
                  "language": "-key-protocol",
                  "version": "2023.1",
                  "key": "-key-PropertyDef-name"
               },
               "value": "newValue"
            },
            {
               "property": {
                  "language": "-key-protocol",
                  "version": "2023.1",
                  "key": "-key-PropertyDef-mayBeNull"
               },
               "value": "false"
            },
            {
               "property": {
                  "language": "-key-protocol",
                  "version": "2023.1",
                  "key": "-key-PropertyDef-isList"
               },
               "value": "false"
            },
            {
               "property": {
                  "language": "-key-protocol",
                  "version": "2023.1",
                  "key": "-key-PropertyDef-isOptional"
               },
               "value": "false"
            },
            {
               "property": {
                  "language": "-key-protocol",
                  "version": "2023.1",
                  "key": "-key-PropertyDef-validate"
               },
               "value": ""
            }
         ],
         "containments": [],
         "references": [
            {
               "reference": {
                  "language": "-key-protocol",
                  "version": "2023.1",
                  "key": "-key-PropertyDef-type"
               },
               "targets": [
                  {
                     "resolveInfo": "String",
                     "reference": "ID-3"
                  }
               ]
            }
         ],
         "annotations": [],
         "parent": "ID-93"
      },
      {
         "id": "ID-91",
         "classifier": {
            "language": "-key-protocol",
            "version": "2023.1",
            "key": "-key-ObjectType"
         },
         "properties": [
            {
               "property": {
                  "language": "-key-protocol",
                  "version": "2023.1",
                  "key": "-key-Type-name"
               },
               "value": "DeletePropery"
            }
         ],
         "containments": [
            {
               "containment": {
                  "language": "-key-protocol",
                  "version": "2023.1",
                  "key": "-key-ObjectType-properties"
               },
               "children": [
                  "ID-101",
                  "ID-103"
               ]
            }
         ],
         "references": [],
         "annotations": [],
         "parent": "ID-7"
      },
      {
         "id": "ID-101",
         "classifier": {
            "language": "-key-protocol",
            "version": "2023.1",
            "key": "-key-PropertyDef"
         },
         "properties": [
            {
               "property": {
                  "language": "-key-protocol",
                  "version": "2023.1",
                  "key": "-key-PropertyDef-name"
               },
               "value": "node"
            },
            {
               "property": {
                  "language": "-key-protocol",
                  "version": "2023.1",
                  "key": "-key-PropertyDef-mayBeNull"
               },
               "value": "false"
            },
            {
               "property": {
                  "language": "-key-protocol",
                  "version": "2023.1",
                  "key": "-key-PropertyDef-isList"
               },
               "value": "false"
            },
            {
               "property": {
                  "language": "-key-protocol",
                  "version": "2023.1",
                  "key": "-key-PropertyDef-isOptional"
               },
               "value": "false"
            },
            {
               "property": {
                  "language": "-key-protocol",
                  "version": "2023.1",
                  "key": "-key-PropertyDef-validate"
               },
               "value": ""
            }
         ],
         "containments": [],
         "references": [
            {
               "reference": {
                  "language": "-key-protocol",
                  "version": "2023.1",
                  "key": "-key-PropertyDef-type"
               },
               "targets": [
                  {
                     "resolveInfo": "LionWebId",
                     "reference": "ID-22"
                  }
               ]
            }
         ],
         "annotations": [],
         "parent": "ID-91"
      },
      {
         "id": "ID-103",
         "classifier": {
            "language": "-key-protocol",
            "version": "2023.1",
            "key": "-key-PropertyDef"
         },
         "properties": [
            {
               "property": {
                  "language": "-key-protocol",
                  "version": "2023.1",
                  "key": "-key-PropertyDef-name"
               },
               "value": "property"
            },
            {
               "property": {
                  "language": "-key-protocol",
                  "version": "2023.1",
                  "key": "-key-PropertyDef-mayBeNull"
               },
               "value": "false"
            },
            {
               "property": {
                  "language": "-key-protocol",
                  "version": "2023.1",
                  "key": "-key-PropertyDef-isList"
               },
               "value": "false"
            },
            {
               "property": {
                  "language": "-key-protocol",
                  "version": "2023.1",
                  "key": "-key-PropertyDef-isOptional"
               },
               "value": "false"
            },
            {
               "property": {
                  "language": "-key-protocol",
                  "version": "2023.1",
                  "key": "-key-PropertyDef-validate"
               },
               "value": ""
            }
         ],
         "containments": [],
         "references": [
            {
               "reference": {
                  "language": "-key-protocol",
                  "version": "2023.1",
                  "key": "-key-PropertyDef-type"
               },
               "targets": [
                  {
                     "resolveInfo": "LionWebJsonPointer",
                     "reference": "ID-20"
                  }
               ]
            }
         ],
         "annotations": [],
         "parent": "ID-91"
      },
      {
         "id": "ID-114",
         "classifier": {
            "language": "-key-protocol",
            "version": "2023.1",
            "key": "-key-ObjectType"
         },
         "properties": [
            {
               "property": {
                  "language": "-key-protocol",
                  "version": "2023.1",
                  "key": "-key-Type-name"
               },
               "value": "AddChild"
            }
         ],
         "containments": [
            {
               "containment": {
                  "language": "-key-protocol",
                  "version": "2023.1",
                  "key": "-key-ObjectType-properties"
               },
               "children": [
                  "ID-115",
                  "ID-116",
                  "ID-117",
                  "ID-118"
               ]
            }
         ],
         "references": [],
         "annotations": [],
         "parent": "ID-7"
      },
      {
         "id": "ID-115",
         "classifier": {
            "language": "-key-protocol",
            "version": "2023.1",
            "key": "-key-PropertyDef"
         },
         "properties": [
            {
               "property": {
                  "language": "-key-protocol",
                  "version": "2023.1",
                  "key": "-key-PropertyDef-name"
               },
               "value": "parent"
            },
            {
               "property": {
                  "language": "-key-protocol",
                  "version": "2023.1",
                  "key": "-key-PropertyDef-mayBeNull"
               },
               "value": "false"
            },
            {
               "property": {
                  "language": "-key-protocol",
                  "version": "2023.1",
                  "key": "-key-PropertyDef-isList"
               },
               "value": "false"
            },
            {
               "property": {
                  "language": "-key-protocol",
                  "version": "2023.1",
                  "key": "-key-PropertyDef-isOptional"
               },
               "value": "false"
            },
            {
               "property": {
                  "language": "-key-protocol",
                  "version": "2023.1",
                  "key": "-key-PropertyDef-validate"
               },
               "value": ""
            }
         ],
         "containments": [],
         "references": [
            {
               "reference": {
                  "language": "-key-protocol",
                  "version": "2023.1",
                  "key": "-key-PropertyDef-type"
               },
               "targets": [
                  {
                     "resolveInfo": "LionWebId",
                     "reference": "ID-22"
                  }
               ]
            }
         ],
         "annotations": [],
         "parent": "ID-114"
      },
      {
         "id": "ID-116",
         "classifier": {
            "language": "-key-protocol",
            "version": "2023.1",
            "key": "-key-PropertyDef"
         },
         "properties": [
            {
               "property": {
                  "language": "-key-protocol",
                  "version": "2023.1",
                  "key": "-key-PropertyDef-name"
               },
               "value": "newChild"
            },
            {
               "property": {
                  "language": "-key-protocol",
                  "version": "2023.1",
                  "key": "-key-PropertyDef-mayBeNull"
               },
               "value": "false"
            },
            {
               "property": {
                  "language": "-key-protocol",
                  "version": "2023.1",
                  "key": "-key-PropertyDef-isList"
               },
               "value": "false"
            },
            {
               "property": {
                  "language": "-key-protocol",
                  "version": "2023.1",
                  "key": "-key-PropertyDef-isOptional"
               },
               "value": "false"
            },
            {
               "property": {
                  "language": "-key-protocol",
                  "version": "2023.1",
                  "key": "-key-PropertyDef-validate"
               },
               "value": ""
            }
         ],
         "containments": [],
         "references": [
            {
               "reference": {
                  "language": "-key-protocol",
                  "version": "2023.1",
                  "key": "-key-PropertyDef-type"
               },
               "targets": [
                  {
                     "resolveInfo": "LionWebDeltaJsonChunk",
                     "reference": "ID-48"
                  }
               ]
            }
         ],
         "annotations": [],
         "parent": "ID-114"
      },
      {
         "id": "ID-117",
         "classifier": {
            "language": "-key-protocol",
            "version": "2023.1",
            "key": "-key-PropertyDef"
         },
         "properties": [
            {
               "property": {
                  "language": "-key-protocol",
                  "version": "2023.1",
                  "key": "-key-PropertyDef-name"
               },
               "value": "containment"
            },
            {
               "property": {
                  "language": "-key-protocol",
                  "version": "2023.1",
                  "key": "-key-PropertyDef-mayBeNull"
               },
               "value": "false"
            },
            {
               "property": {
                  "language": "-key-protocol",
                  "version": "2023.1",
                  "key": "-key-PropertyDef-isList"
               },
               "value": "false"
            },
            {
               "property": {
                  "language": "-key-protocol",
                  "version": "2023.1",
                  "key": "-key-PropertyDef-isOptional"
               },
               "value": "false"
            },
            {
               "property": {
                  "language": "-key-protocol",
                  "version": "2023.1",
                  "key": "-key-PropertyDef-validate"
               },
               "value": ""
            }
         ],
         "containments": [],
         "references": [
            {
               "reference": {
                  "language": "-key-protocol",
                  "version": "2023.1",
                  "key": "-key-PropertyDef-type"
               },
               "targets": [
                  {
                     "resolveInfo": "LionWebJsonPointer",
                     "reference": "ID-20"
                  }
               ]
            }
         ],
         "annotations": [],
         "parent": "ID-114"
      },
      {
         "id": "ID-118",
         "classifier": {
            "language": "-key-protocol",
            "version": "2023.1",
            "key": "-key-PropertyDef"
         },
         "properties": [
            {
               "property": {
                  "language": "-key-protocol",
                  "version": "2023.1",
                  "key": "-key-PropertyDef-name"
               },
               "value": "index"
            },
            {
               "property": {
                  "language": "-key-protocol",
                  "version": "2023.1",
                  "key": "-key-PropertyDef-mayBeNull"
               },
               "value": "false"
            },
            {
               "property": {
                  "language": "-key-protocol",
                  "version": "2023.1",
                  "key": "-key-PropertyDef-isList"
               },
               "value": "false"
            },
            {
               "property": {
                  "language": "-key-protocol",
                  "version": "2023.1",
                  "key": "-key-PropertyDef-isOptional"
               },
               "value": "false"
            },
            {
               "property": {
                  "language": "-key-protocol",
                  "version": "2023.1",
                  "key": "-key-PropertyDef-validate"
               },
               "value": ""
            }
         ],
         "containments": [],
         "references": [
            {
               "reference": {
                  "language": "-key-protocol",
                  "version": "2023.1",
                  "key": "-key-PropertyDef-type"
               },
               "targets": [
                  {
                     "resolveInfo": "Number",
                     "reference": "ID-78"
                  }
               ]
            }
         ],
         "annotations": [],
         "parent": "ID-114"
      },
      {
         "id": "ID-92",
         "classifier": {
            "language": "-key-protocol",
            "version": "2023.1",
            "key": "-key-ObjectType"
         },
         "properties": [
            {
               "property": {
                  "language": "-key-protocol",
                  "version": "2023.1",
                  "key": "-key-Type-name"
               },
               "value": "DeleteChild"
            }
         ],
         "containments": [
            {
               "containment": {
                  "language": "-key-protocol",
                  "version": "2023.1",
                  "key": "-key-ObjectType-properties"
               },
               "children": [
                  "ID-105",
                  "ID-106",
                  "ID-107",
                  "ID-108"
               ]
            }
         ],
         "references": [],
         "annotations": [],
         "parent": "ID-7"
      },
      {
         "id": "ID-105",
         "classifier": {
            "language": "-key-protocol",
            "version": "2023.1",
            "key": "-key-PropertyDef"
         },
         "properties": [
            {
               "property": {
                  "language": "-key-protocol",
                  "version": "2023.1",
                  "key": "-key-PropertyDef-name"
               },
               "value": "parent"
            },
            {
               "property": {
                  "language": "-key-protocol",
                  "version": "2023.1",
                  "key": "-key-PropertyDef-mayBeNull"
               },
               "value": "false"
            },
            {
               "property": {
                  "language": "-key-protocol",
                  "version": "2023.1",
                  "key": "-key-PropertyDef-isList"
               },
               "value": "false"
            },
            {
               "property": {
                  "language": "-key-protocol",
                  "version": "2023.1",
                  "key": "-key-PropertyDef-isOptional"
               },
               "value": "false"
            },
            {
               "property": {
                  "language": "-key-protocol",
                  "version": "2023.1",
                  "key": "-key-PropertyDef-validate"
               },
               "value": ""
            }
         ],
         "containments": [],
         "references": [
            {
               "reference": {
                  "language": "-key-protocol",
                  "version": "2023.1",
                  "key": "-key-PropertyDef-type"
               },
               "targets": [
                  {
                     "resolveInfo": "LionWebId",
                     "reference": "ID-22"
                  }
               ]
            }
         ],
         "annotations": [],
         "parent": "ID-92"
      },
      {
         "id": "ID-106",
         "classifier": {
            "language": "-key-protocol",
            "version": "2023.1",
            "key": "-key-PropertyDef"
         },
         "properties": [
            {
               "property": {
                  "language": "-key-protocol",
                  "version": "2023.1",
                  "key": "-key-PropertyDef-name"
               },
               "value": "deletedChild"
            },
            {
               "property": {
                  "language": "-key-protocol",
                  "version": "2023.1",
                  "key": "-key-PropertyDef-mayBeNull"
               },
               "value": "false"
            },
            {
               "property": {
                  "language": "-key-protocol",
                  "version": "2023.1",
                  "key": "-key-PropertyDef-isList"
               },
               "value": "false"
            },
            {
               "property": {
                  "language": "-key-protocol",
                  "version": "2023.1",
                  "key": "-key-PropertyDef-isOptional"
               },
               "value": "false"
            },
            {
               "property": {
                  "language": "-key-protocol",
                  "version": "2023.1",
                  "key": "-key-PropertyDef-validate"
               },
               "value": ""
            }
         ],
         "containments": [],
         "references": [
            {
               "reference": {
                  "language": "-key-protocol",
                  "version": "2023.1",
                  "key": "-key-PropertyDef-type"
               },
               "targets": [
                  {
                     "resolveInfo": "LionWebId",
                     "reference": "ID-22"
                  }
               ]
            }
         ],
         "annotations": [],
         "parent": "ID-92"
      },
      {
         "id": "ID-107",
         "classifier": {
            "language": "-key-protocol",
            "version": "2023.1",
            "key": "-key-PropertyDef"
         },
         "properties": [
            {
               "property": {
                  "language": "-key-protocol",
                  "version": "2023.1",
                  "key": "-key-PropertyDef-name"
               },
               "value": "containment"
            },
            {
               "property": {
                  "language": "-key-protocol",
                  "version": "2023.1",
                  "key": "-key-PropertyDef-mayBeNull"
               },
               "value": "false"
            },
            {
               "property": {
                  "language": "-key-protocol",
                  "version": "2023.1",
                  "key": "-key-PropertyDef-isList"
               },
               "value": "false"
            },
            {
               "property": {
                  "language": "-key-protocol",
                  "version": "2023.1",
                  "key": "-key-PropertyDef-isOptional"
               },
               "value": "false"
            },
            {
               "property": {
                  "language": "-key-protocol",
                  "version": "2023.1",
                  "key": "-key-PropertyDef-validate"
               },
               "value": ""
            }
         ],
         "containments": [],
         "references": [
            {
               "reference": {
                  "language": "-key-protocol",
                  "version": "2023.1",
                  "key": "-key-PropertyDef-type"
               },
               "targets": [
                  {
                     "resolveInfo": "LionWebJsonPointer",
                     "reference": "ID-20"
                  }
               ]
            }
         ],
         "annotations": [],
         "parent": "ID-92"
      },
      {
         "id": "ID-108",
         "classifier": {
            "language": "-key-protocol",
            "version": "2023.1",
            "key": "-key-PropertyDef"
         },
         "properties": [
            {
               "property": {
                  "language": "-key-protocol",
                  "version": "2023.1",
                  "key": "-key-PropertyDef-name"
               },
               "value": "index"
            },
            {
               "property": {
                  "language": "-key-protocol",
                  "version": "2023.1",
                  "key": "-key-PropertyDef-mayBeNull"
               },
               "value": "false"
            },
            {
               "property": {
                  "language": "-key-protocol",
                  "version": "2023.1",
                  "key": "-key-PropertyDef-isList"
               },
               "value": "false"
            },
            {
               "property": {
                  "language": "-key-protocol",
                  "version": "2023.1",
                  "key": "-key-PropertyDef-isOptional"
               },
               "value": "false"
            },
            {
               "property": {
                  "language": "-key-protocol",
                  "version": "2023.1",
                  "key": "-key-PropertyDef-validate"
               },
               "value": ""
            }
         ],
         "containments": [],
         "references": [
            {
               "reference": {
                  "language": "-key-protocol",
                  "version": "2023.1",
                  "key": "-key-PropertyDef-type"
               },
               "targets": [
                  {
                     "resolveInfo": "Number",
                     "reference": "ID-78"
                  }
               ]
            }
         ],
         "annotations": [],
         "parent": "ID-92"
      },
      {
         "id": "ID-109",
         "classifier": {
            "language": "-key-protocol",
            "version": "2023.1",
            "key": "-key-ObjectType"
         },
         "properties": [
            {
               "property": {
                  "language": "-key-protocol",
                  "version": "2023.1",
                  "key": "-key-Type-name"
               },
               "value": "ReplaceChild"
            }
         ],
         "containments": [
            {
               "containment": {
                  "language": "-key-protocol",
                  "version": "2023.1",
                  "key": "-key-ObjectType-properties"
               },
               "children": [
                  "ID-110",
                  "ID-111",
                  "ID-112",
                  "ID-113",
                  "ID-124"
               ]
            }
         ],
         "references": [],
         "annotations": [],
         "parent": "ID-7"
      },
      {
         "id": "ID-110",
         "classifier": {
            "language": "-key-protocol",
            "version": "2023.1",
            "key": "-key-PropertyDef"
         },
         "properties": [
            {
               "property": {
                  "language": "-key-protocol",
                  "version": "2023.1",
                  "key": "-key-PropertyDef-name"
               },
               "value": "parent"
            },
            {
               "property": {
                  "language": "-key-protocol",
                  "version": "2023.1",
                  "key": "-key-PropertyDef-mayBeNull"
               },
               "value": "false"
            },
            {
               "property": {
                  "language": "-key-protocol",
                  "version": "2023.1",
                  "key": "-key-PropertyDef-isList"
               },
               "value": "false"
            },
            {
               "property": {
                  "language": "-key-protocol",
                  "version": "2023.1",
                  "key": "-key-PropertyDef-isOptional"
               },
               "value": "false"
            },
            {
               "property": {
                  "language": "-key-protocol",
                  "version": "2023.1",
                  "key": "-key-PropertyDef-validate"
               },
               "value": ""
            }
         ],
         "containments": [],
         "references": [
            {
               "reference": {
                  "language": "-key-protocol",
                  "version": "2023.1",
                  "key": "-key-PropertyDef-type"
               },
               "targets": [
                  {
                     "resolveInfo": "LionWebId",
                     "reference": "ID-22"
                  }
               ]
            }
         ],
         "annotations": [],
         "parent": "ID-109"
      },
      {
         "id": "ID-111",
         "classifier": {
            "language": "-key-protocol",
            "version": "2023.1",
            "key": "-key-PropertyDef"
         },
         "properties": [
            {
               "property": {
                  "language": "-key-protocol",
                  "version": "2023.1",
                  "key": "-key-PropertyDef-name"
               },
               "value": "newChild"
            },
            {
               "property": {
                  "language": "-key-protocol",
                  "version": "2023.1",
                  "key": "-key-PropertyDef-mayBeNull"
               },
               "value": "false"
            },
            {
               "property": {
                  "language": "-key-protocol",
                  "version": "2023.1",
                  "key": "-key-PropertyDef-isList"
               },
               "value": "false"
            },
            {
               "property": {
                  "language": "-key-protocol",
                  "version": "2023.1",
                  "key": "-key-PropertyDef-isOptional"
               },
               "value": "false"
            },
            {
               "property": {
                  "language": "-key-protocol",
                  "version": "2023.1",
                  "key": "-key-PropertyDef-validate"
               },
               "value": ""
            }
         ],
         "containments": [],
         "references": [
            {
               "reference": {
                  "language": "-key-protocol",
                  "version": "2023.1",
                  "key": "-key-PropertyDef-type"
               },
               "targets": [
                  {
                     "resolveInfo": "LionWebDeltaJsonChunk",
                     "reference": "ID-48"
                  }
               ]
            }
         ],
         "annotations": [],
         "parent": "ID-109"
      },
      {
         "id": "ID-112",
         "classifier": {
            "language": "-key-protocol",
            "version": "2023.1",
            "key": "-key-PropertyDef"
         },
         "properties": [
            {
               "property": {
                  "language": "-key-protocol",
                  "version": "2023.1",
                  "key": "-key-PropertyDef-name"
               },
               "value": "containment"
            },
            {
               "property": {
                  "language": "-key-protocol",
                  "version": "2023.1",
                  "key": "-key-PropertyDef-mayBeNull"
               },
               "value": "false"
            },
            {
               "property": {
                  "language": "-key-protocol",
                  "version": "2023.1",
                  "key": "-key-PropertyDef-isList"
               },
               "value": "false"
            },
            {
               "property": {
                  "language": "-key-protocol",
                  "version": "2023.1",
                  "key": "-key-PropertyDef-isOptional"
               },
               "value": "false"
            },
            {
               "property": {
                  "language": "-key-protocol",
                  "version": "2023.1",
                  "key": "-key-PropertyDef-validate"
               },
               "value": ""
            }
         ],
         "containments": [],
         "references": [
            {
               "reference": {
                  "language": "-key-protocol",
                  "version": "2023.1",
                  "key": "-key-PropertyDef-type"
               },
               "targets": [
                  {
                     "resolveInfo": "LionWebJsonPointer",
                     "reference": "ID-20"
                  }
               ]
            }
         ],
         "annotations": [],
         "parent": "ID-109"
      },
      {
         "id": "ID-113",
         "classifier": {
            "language": "-key-protocol",
            "version": "2023.1",
            "key": "-key-PropertyDef"
         },
         "properties": [
            {
               "property": {
                  "language": "-key-protocol",
                  "version": "2023.1",
                  "key": "-key-PropertyDef-name"
               },
               "value": "index"
            },
            {
               "property": {
                  "language": "-key-protocol",
                  "version": "2023.1",
                  "key": "-key-PropertyDef-mayBeNull"
               },
               "value": "false"
            },
            {
               "property": {
                  "language": "-key-protocol",
                  "version": "2023.1",
                  "key": "-key-PropertyDef-isList"
               },
               "value": "false"
            },
            {
               "property": {
                  "language": "-key-protocol",
                  "version": "2023.1",
                  "key": "-key-PropertyDef-isOptional"
               },
               "value": "false"
            },
            {
               "property": {
                  "language": "-key-protocol",
                  "version": "2023.1",
                  "key": "-key-PropertyDef-validate"
               },
               "value": ""
            }
         ],
         "containments": [],
         "references": [
            {
               "reference": {
                  "language": "-key-protocol",
                  "version": "2023.1",
                  "key": "-key-PropertyDef-type"
               },
               "targets": [
                  {
                     "resolveInfo": "Number",
                     "reference": "ID-78"
                  }
               ]
            }
         ],
         "annotations": [],
         "parent": "ID-109"
      },
      {
         "id": "ID-124",
         "classifier": {
            "language": "-key-protocol",
            "version": "2023.1",
            "key": "-key-PropertyDef"
         },
         "properties": [
            {
               "property": {
                  "language": "-key-protocol",
                  "version": "2023.1",
                  "key": "-key-PropertyDef-name"
               },
               "value": "replacedChild"
            },
            {
               "property": {
                  "language": "-key-protocol",
                  "version": "2023.1",
                  "key": "-key-PropertyDef-mayBeNull"
               },
               "value": "false"
            },
            {
               "property": {
                  "language": "-key-protocol",
                  "version": "2023.1",
                  "key": "-key-PropertyDef-isList"
               },
               "value": "false"
            },
            {
               "property": {
                  "language": "-key-protocol",
                  "version": "2023.1",
                  "key": "-key-PropertyDef-isOptional"
               },
               "value": "false"
            },
            {
               "property": {
                  "language": "-key-protocol",
                  "version": "2023.1",
                  "key": "-key-PropertyDef-validate"
               },
               "value": ""
            }
         ],
         "containments": [],
         "references": [
            {
               "reference": {
                  "language": "-key-protocol",
                  "version": "2023.1",
                  "key": "-key-PropertyDef-type"
               },
               "targets": [
                  {
                     "resolveInfo": "LionWebId",
                     "reference": "ID-22"
                  }
               ]
            }
         ],
         "annotations": [],
         "parent": "ID-109"
      },
      {
         "id": "ID-8",
         "classifier": {
            "language": "-key-protocol",
            "version": "2023.1",
            "key": "-key-PropertyDef"
         },
         "properties": [
            {
               "property": {
                  "language": "-key-protocol",
                  "version": "2023.1",
                  "key": "-key-PropertyDef-name"
               },
               "value": "commandId"
            },
            {
               "property": {
                  "language": "-key-protocol",
                  "version": "2023.1",
                  "key": "-key-PropertyDef-mayBeNull"
               },
               "value": "false"
            },
            {
               "property": {
                  "language": "-key-protocol",
                  "version": "2023.1",
                  "key": "-key-PropertyDef-isList"
               },
               "value": "false"
            },
            {
               "property": {
                  "language": "-key-protocol",
                  "version": "2023.1",
                  "key": "-key-PropertyDef-isOptional"
               },
               "value": "false"
            },
            {
               "property": {
                  "language": "-key-protocol",
                  "version": "2023.1",
                  "key": "-key-PropertyDef-validate"
               },
               "value": ""
            }
         ],
         "containments": [],
         "references": [
            {
               "reference": {
                  "language": "-key-protocol",
                  "version": "2023.1",
                  "key": "-key-PropertyDef-type"
               },
               "targets": [
                  {
                     "resolveInfo": "String",
                     "reference": "ID-3"
                  }
               ]
            }
         ],
         "annotations": [],
         "parent": "ID-7"
      },
      {
         "id": "ID-9",
         "classifier": {
            "language": "-key-protocol",
            "version": "2023.1",
            "key": "-key-PropertyDef"
         },
         "properties": [
            {
               "property": {
                  "language": "-key-protocol",
                  "version": "2023.1",
                  "key": "-key-PropertyDef-name"
               },
               "value": "messageKind"
            },
            {
               "property": {
                  "language": "-key-protocol",
                  "version": "2023.1",
                  "key": "-key-PropertyDef-mayBeNull"
               },
               "value": "false"
            },
            {
               "property": {
                  "language": "-key-protocol",
                  "version": "2023.1",
                  "key": "-key-PropertyDef-isList"
               },
               "value": "false"
            },
            {
               "property": {
                  "language": "-key-protocol",
                  "version": "2023.1",
                  "key": "-key-PropertyDef-isOptional"
               },
               "value": "false"
            },
            {
               "property": {
                  "language": "-key-protocol",
                  "version": "2023.1",
                  "key": "-key-PropertyDef-validate"
               },
               "value": ""
            }
         ],
         "containments": [],
         "references": [
            {
               "reference": {
                  "language": "-key-protocol",
                  "version": "2023.1",
                  "key": "-key-PropertyDef-type"
               },
               "targets": [
                  {
                     "resolveInfo": "String",
                     "reference": "ID-3"
                  }
               ]
            }
         ],
         "annotations": [],
         "parent": "ID-7"
      },
      {
         "id": "ID-16",
         "classifier": {
            "language": "-key-protocol",
            "version": "2023.1",
            "key": "-key-PropertyDef"
         },
         "properties": [
            {
               "property": {
                  "language": "-key-protocol",
                  "version": "2023.1",
                  "key": "-key-PropertyDef-name"
               },
               "value": "protocolMessage"
            },
            {
               "property": {
                  "language": "-key-protocol",
                  "version": "2023.1",
                  "key": "-key-PropertyDef-mayBeNull"
               },
               "value": "false"
            },
            {
               "property": {
                  "language": "-key-protocol",
                  "version": "2023.1",
                  "key": "-key-PropertyDef-isList"
               },
               "value": "false"
            },
            {
               "property": {
                  "language": "-key-protocol",
                  "version": "2023.1",
                  "key": "-key-PropertyDef-isOptional"
               },
               "value": "false"
            },
            {
               "property": {
                  "language": "-key-protocol",
                  "version": "2023.1",
                  "key": "-key-PropertyDef-validate"
               },
               "value": ""
            }
         ],
         "containments": [],
         "references": [
            {
               "reference": {
                  "language": "-key-protocol",
                  "version": "2023.1",
                  "key": "-key-PropertyDef-type"
               },
               "targets": [
                  {
                     "resolveInfo": "ProtocolMessage",
                     "reference": "ID-4"
                  }
               ]
            }
         ],
         "annotations": [],
         "parent": "ID-7"
      }
   ]
}